heroku_mia_sdk/__init__.py
heroku_mia_sdk/agent.py
heroku_mia_sdk/chat.py
heroku_mia_sdk/common.py
heroku_mia_sdk/types.py
heroku_mia_sdk-0.1.0.dist-info/licenses/LICENSE
heroku_mia_sdk-0.1.0.dist-info/METADATA
heroku_mia_sdk-0.1.0.dist-info/WHEEL
heroku_mia_sdk-0.1.0.dist-info/top_level.txt
heroku_mia_sdk-0.1.0.dist-info/RECORD
