Metadata-Version: 2.4
Name: heroku-mia-sdk
Version: 0.1.0
Summary: Heroku MIA SDK for Python - AI inference client for Heroku's managed inference API
Home-page: https://github.com/heroku/heroku-mia-sdk-python
Author: Heroku
Author-email: Heroku <support@heroku.com>
Maintainer-email: Heroku <support@heroku.com>
License: MIT
Project-URL: Homepage, https://github.com/heroku/heroku-mia-sdk-python
Project-URL: Documentation, https://github.com/heroku/heroku-mia-sdk-python#readme
Project-URL: Repository, https://github.com/heroku/heroku-mia-sdk-python
Project-URL: Bug Tracker, https://github.com/heroku/heroku-mia-sdk-python/issues
Keywords: heroku,ai,inference,langchain,llm
Classifier: Development Status :: 3 - Alpha
Classifier: Intended Audience :: Developers
Classifier: License :: OSI Approved :: MIT License
Classifier: Programming Language :: Python :: 3
Classifier: Programming Language :: Python :: 3.8
Classifier: Programming Language :: Python :: 3.9
Classifier: Programming Language :: Python :: 3.10
Classifier: Programming Language :: Python :: 3.11
Classifier: Programming Language :: Python :: 3.12
Classifier: Topic :: Software Development :: Libraries :: Python Modules
Classifier: Topic :: Scientific/Engineering :: Artificial Intelligence
Requires-Python: >=3.8
License-File: LICENSE
Requires-Dist: langchain-core>=0.1.0
Requires-Dist: httpx>=0.24.0
Requires-Dist: pydantic>=2.0.0
Provides-Extra: dev
Requires-Dist: pytest>=7.0.0; extra == "dev"
Requires-Dist: pytest-asyncio>=0.21.0; extra == "dev"
Requires-Dist: black>=23.0.0; extra == "dev"
Requires-Dist: isort>=5.12.0; extra == "dev"
Requires-Dist: flake8>=6.0.0; extra == "dev"
Requires-Dist: mypy>=1.0.0; extra == "dev"
Dynamic: author
Dynamic: home-page
Dynamic: license-file
Dynamic: requires-python
